insteon_frontend/__init__.py
insteon_frontend/constants.py
insteon_frontend/entrypoint.53839f01e3bb1ec2.js
insteon_frontend/entrypoint.53839f01e3bb1ec2.js.br
insteon_frontend/py.typed
insteon_frontend/frontend_es5/1007.0c434c12ca5518c0.js
insteon_frontend/frontend_es5/1007.0c434c12ca5518c0.js.br
insteon_frontend/frontend_es5/1007.0c434c12ca5518c0.js.map
insteon_frontend/frontend_es5/101.e3aa08813fb6fcea.js
insteon_frontend/frontend_es5/101.e3aa08813fb6fcea.js.br
insteon_frontend/frontend_es5/101.e3aa08813fb6fcea.js.map
insteon_frontend/frontend_es5/1043.d166c08cc5dce398.js
insteon_frontend/frontend_es5/1043.d166c08cc5dce398.js.br
insteon_frontend/frontend_es5/1043.d166c08cc5dce398.js.map
insteon_frontend/frontend_es5/1055.840771461a82efa7.js
insteon_frontend/frontend_es5/1055.840771461a82efa7.js.LICENSE.txt
insteon_frontend/frontend_es5/1055.840771461a82efa7.js.br
insteon_frontend/frontend_es5/1055.840771461a82efa7.js.map
insteon_frontend/frontend_es5/110.d78f0ae3453d7293.js
insteon_frontend/frontend_es5/110.d78f0ae3453d7293.js.LICENSE.txt
insteon_frontend/frontend_es5/110.d78f0ae3453d7293.js.br
insteon_frontend/frontend_es5/110.d78f0ae3453d7293.js.map
insteon_frontend/frontend_es5/1120.a44c64ce3e80bcd8.js
insteon_frontend/frontend_es5/1120.a44c64ce3e80bcd8.js.br
insteon_frontend/frontend_es5/1120.a44c64ce3e80bcd8.js.map
insteon_frontend/frontend_es5/113.ead1dc1e544ad0d3.js
insteon_frontend/frontend_es5/113.ead1dc1e544ad0d3.js.br
insteon_frontend/frontend_es5/113.ead1dc1e544ad0d3.js.map
insteon_frontend/frontend_es5/1157.ae1e3f382d5b1171.js
insteon_frontend/frontend_es5/1157.ae1e3f382d5b1171.js.br
insteon_frontend/frontend_es5/1157.ae1e3f382d5b1171.js.map
insteon_frontend/frontend_es5/1213.b1660263998e78ed.js
insteon_frontend/frontend_es5/1213.b1660263998e78ed.js.br
insteon_frontend/frontend_es5/1213.b1660263998e78ed.js.map
insteon_frontend/frontend_es5/1279.deb1da087a002e10.js
insteon_frontend/frontend_es5/1279.deb1da087a002e10.js.br
insteon_frontend_home_assistant-0.6.0.dist-info/licenses/LICENSE
insteon_frontend_home_assistant-0.6.0.dist-info/METADATA
insteon_frontend_home_assistant-0.6.0.dist-info/WHEEL
insteon_frontend_home_assistant-0.6.0.dist-info/top_level.txt
insteon_frontend_home_assistant-0.6.0.dist-info/RECORD
