Metadata-Version: 2.4
Name: insteon-frontend-home-assistant
Version: 0.6.0
Summary: The Insteon frontend for Home Assistant
Author-email: Tom Harris <pyinsteon@harrisnj.net>
License: MIT License
Project-URL: Homepage, https://github.com/pyinsteon/insteon-panel
Platform: any
Requires-Python: >=3.10.0
License-File: LICENSE
Dynamic: license-file
